turtlevcs/__init__.py
turtlevcs/__main__.py
turtlevcs/colors.py
turtlevcs/package_information.py
turtlevcs/service.py
turtlevcs/turtle.py
turtlevcs/turtle_app.py
turtlevcs/turtle_plugin.py
turtlevcs/dialogs/__init__.py
turtlevcs/dialogs/about.py
turtlevcs/dialogs/add.py
turtlevcs/dialogs/base.py
turtlevcs/dialogs/checkout.py
turtlevcs/dialogs/clean.py
turtlevcs/dialogs/clone.py
turtlevcs/dialogs/commit.py
turtlevcs/dialogs/commit_table.py
turtlevcs/dialogs/create.py
turtlevcs/dialogs/create_branch.py
turtlevcs/dialogs/create_tag.py
turtlevcs/dialogs/diff.py
turtlevcs/dialogs/diff_file.py
turtlevcs/dialogs/enter_credentials.py
turtlevcs/dialogs/init.py
turtlevcs/dialogs/log.py
turtlevcs/dialogs/merge.py
turtlevcs/dialogs/plugin_installer.py
turtlevcs/dialogs/pull.py
turtlevcs/dialogs/push.py
turtlevcs/dialogs/push_table.py
turtlevcs/dialogs/references.py
turtlevcs/dialogs/remotes.py
turtlevcs/dialogs/reset.py
turtlevcs/dialogs/resolve.py
turtlevcs/dialogs/revert.py
turtlevcs/dialogs/settings.py
turtlevcs/dialogs/stage.py
turtlevcs/dialogs/submodules.py
turtlevcs/dialogs/sync.py
turtlevcs/dialogs/unstage.py
turtlevcs/dialogs/update.py
turtlevcs/dialogs/ui/add.ui
turtlevcs/dialogs/ui/add_submodules.ui
turtlevcs/dialogs/ui/checkout.ui
turtlevcs/dialogs/ui/clean.ui
turtlevcs/dialogs/ui/clone.ui
turtlevcs/dialogs/ui/commit.ui
turtlevcs/dialogs/ui/commit_table.ui
turtlevcs/dialogs/ui/create.ui
turtlevcs/dialogs/ui/diff.ui
turtlevcs/dialogs/ui/enter_credentials.ui
turtlevcs/dialogs/ui/init.ui
turtlevcs/dialogs/ui/log.ui
turtlevcs/dialogs/ui/log_filter.ui
turtlevcs/dialogs/ui/merge.ui
turtlevcs/dialogs/ui/plugin_installer.ui
turtlevcs/dialogs/ui/pull.ui
turtlevcs/dialogs/ui/push.ui
turtlevcs/dialogs/ui/push_table.ui
turtlevcs/dialogs/ui/reference_details.ui
turtlevcs/dialogs/ui/references.ui
turtlevcs/dialogs/ui/remotes.ui
turtlevcs/dialogs/ui/remotes_dialog.ui
turtlevcs/dialogs/ui/remove_submodule.ui
turtlevcs/dialogs/ui/reset.ui
turtlevcs/dialogs/ui/resolve.ui
turtlevcs-0.11.1.dist-info/COPYING
turtlevcs-0.11.1.dist-info/METADATA
turtlevcs-0.11.1.dist-info/WHEEL
turtlevcs-0.11.1.dist-info/top_level.txt
turtlevcs-0.11.1.dist-info/RECORD
