Metadata-Version: 2.1
Name: turtlevcs
Version: 0.11.1
Summary: pygit2 frontend with adwaita style and nautilus plugin
Home-page: https://gitlab.gnome.org/philippun1/turtle
Author: Philipp Unger
Author-email: philipp.unger.1988@gmail.com
License: GPL3
License-File: COPYING
Requires-Dist: dbus-python>=1.3.2
Requires-Dist: pygit2>=1.14.1
Requires-Dist: pygobject>=3.48.0
Requires-Dist: secretstorage>=3.3.0
